cygnsslib/CygDdmId.py
cygnsslib/__init__.py
cygnsslib/analyze_cyg_data.py
cygnsslib/cyg.py
cygnsslib/ddm_stats.py
cygnsslib/plotting.py
cygnsslib/util.py
cygnsslib/cygnss_download/__init__.py
cygnsslib/data_downloader/__init__.py
cygnsslib/data_downloader/cyg_ant_ptrn.py
cygnsslib/data_downloader/download_cyg_rawif.py
cygnsslib/data_downloader/download_cygnss.py
cygnsslib/data_downloader/download_cygnss_sftp.py
cygnsslib/data_downloader/download_srtm.py
cygnsslib/srtm_download/__init__.py
tests/list_loc2kml.py
tests/test_download_cyg_data.py
tests/test_download_srtm.py
tests/test_find_land_prod_from_cvs.py
tests/test_functions.py
tests/test_search_within_circle.py
tests/test_write_sp_within_radius.py
cygnsslib-1.3.21.dist-info/METADATA
cygnsslib-1.3.21.dist-info/WHEEL
cygnsslib-1.3.21.dist-info/top_level.txt
cygnsslib-1.3.21.dist-info/RECORD
