Metadata-Version: 2.1
Name: cygnsslib
Version: 1.3.21
Summary: Toolset for working with CYGNSS data and downloading CYGNSS data from PODAAC
Home-page: https://bitbucket.org/usc_mixil/cygnsslib
Author: Amer Melebari and James D. Campbell
Author-email: amelebar@usc.edu
License: UNKNOWN
Platform: UNKNOWN
Classifier: Programming Language :: Python :: 3
Classifier: Operating System :: OS Independent
Requires-Python: >=3.9
Requires-Dist: geographiclib
Requires-Dist: lxml
Requires-Dist: matplotlib
Requires-Dist: netcdf4
Requires-Dist: numpy
Requires-Dist: openpyxl
Requires-Dist: pandas
Requires-Dist: paramiko
Requires-Dist: pysftp
Requires-Dist: requests
Requires-Dist: tenacity
Requires-Dist: tqdm
